form3publicapi/__init__.py
form3publicapi/api_helper.py
form3publicapi/configuration.py
form3publicapi/form_3_publicapi_client.py
form3publicapi/controllers/__init__.py
form3publicapi/controllers/account_identification_controller.py
form3publicapi/controllers/account_validation_controller.py
form3publicapi/controllers/accounts_controller.py
form3publicapi/controllers/ace_controller.py
form3publicapi/controllers/audit_controller.py
form3publicapi/controllers/base_controller.py
form3publicapi/controllers/branch_identification_controller.py
form3publicapi/controllers/branches_controller.py
form3publicapi/controllers/claims_controller.py
form3publicapi/controllers/direct_debits_controller.py
form3publicapi/controllers/mandates_controller.py
form3publicapi/controllers/metrics_api_controller.py
form3publicapi/controllers/name_verification_api_controller.py
form3publicapi/controllers/o_auth_authorization_controller.py
form3publicapi/controllers/oauth_2_controller.py
form3publicapi/controllers/organisations_controller.py
form3publicapi/controllers/payments_controller.py
form3publicapi/controllers/platformsecurityapi_controller.py
form3publicapi/controllers/query_api_controller.py
form3publicapi/controllers/reports_controller.py
form3publicapi/controllers/roles_controller.py
form3publicapi/controllers/scheme_file_api_controller.py
form3publicapi/controllers/scheme_messages_controller.py
form3publicapi/controllers/subscriptions_controller.py
form3publicapi/controllers/transaction_file_api_controller.py
form3publicapi/controllers/users_controller.py
form3publicapi/exceptions/__init__.py
form3publicapi/exceptions/api_error_exception.py
form3publicapi/exceptions/api_exception.py
form3publicapi/exceptions/metrics_query_response_error_exception.py
form3publicapi/exceptions/o_auth_provider_exception.py
form3publicapi/http/__init__.py
form3publicapi/http/http_call_back.py
form3publicapi/http/http_method_enum.py
form3publicapi/http/http_request.py
vendor_zahra-1.1.1.dist-info/LICENSE
vendor_zahra-1.1.1.dist-info/METADATA
vendor_zahra-1.1.1.dist-info/WHEEL
vendor_zahra-1.1.1.dist-info/top_level.txt
vendor_zahra-1.1.1.dist-info/RECORD
